djanyolo/__init__.py
djanyolo/admin.py
djanyolo/app.py
djanyolo/forms.py
djanyolo/models.py
djanyolo/urls.py
djanyolo/views.py
djanyolo/migrations/0001_initial.py
djanyolo/migrations/0002_auto_20200225_1930.py
djanyolo/migrations/0003_auto_20200227_1539.py
djanyolo/migrations/0004_auto_20200302_1703.py
djanyolo/migrations/0005_auto_20200302_1710.py
djanyolo/migrations/0006_auto_20200304_1910.py
djanyolo/migrations/0007_auto_20200304_1915.py
djanyolo/migrations/0008_auto_20200312_0854.py
djanyolo/migrations/__init__.py
djanyolo-2020.1.0.dist-info/METADATA
djanyolo-2020.1.0.dist-info/WHEEL
djanyolo-2020.1.0.dist-info/entry_points.txt
djanyolo-2020.1.0.dist-info/top_level.txt
djanyolo-2020.1.0.dist-info/RECORD
