Metadata-Version: 2.1
Name: djanyolo
Version: 2020.1.0
Summary: Manage content for YOLO model.
Home-page: https://robomx.com
Author: RoboMx Team
Author-email: ask@robomx.tech
License: MIT
Keywords: yolo,djanyolo,django
Platform: UNKNOWN
Requires-Dist: asgiref (==3.2.5)
Requires-Dist: autocorrect (==0.4.4)
Requires-Dist: Django (>=2.0.7)
Requires-Dist: opencv-python (==4.2.0.32)
Requires-Dist: pytz (==2019.3)
Requires-Dist: sqlparse (==0.3.1)
